{
    "name": "Duplex",
    "url": "http://fontdeck.com/typeface/duplex",
    "slug": "duplex",
    "use": "heading",
    "classification": [
        "Display",
        "Experimental",
        "Display",
        "Decorative"
    ],
    "foundry": "Fontfabric",
    "designer": [
        "Svetoslav Simov"
    ],
    "language": [
        "latin"
    ],
    "tags": [
        "modern",
        "minimalism",
        "bold",
        "elegant",
        "simple",
        "rounded",
        "round"
    ],
    "variations": [
        {
            "name": "Regular",
            "description": "n4",
            "url": "http://fontdeck.com/font/duplex/regular",
            "css": {
                "font-family": "Duplex Regular",
                "font-weight": "400",
                "font-style": "normal"
            },
            "fontdeck": {
                "id": "3001",
                "slug": "regular",
                "price": "$12.50"
            }
        }
    ],
    "fontdeck": {
        "id": "700",
        "slug": "duplex"
    },
    "generatedAt": 1437609742567
}