{
    "name": "FS Elliot Web Cyrillic",
    "url": "http://fontdeck.com/typeface/fselliotwebcyrillic",
    "slug": "fselliotwebcyrillic",
    "use": "heading",
    "classification": [
        "Sans Serif",
        "Geometric"
    ],
    "foundry": "Fontsmith",
    "designer": [
        "Nick Job"
    ],
    "language": [
        "latin",
        "cyrillic"
    ],
    "tags": [
        "open",
        "british",
        "clean",
        "optimistic",
        "legible"
    ],
    "variations": [
        {
            "name": "Thin",
            "description": "n1",
            "url": "http://fontdeck.com/font/fselliotwebcyrillic/thin",
            "css": {
                "font-family": "FS Elliot Web Cyrillic Thin",
                "font-weight": "100",
                "font-style": "normal"
            },
            "fontdeck": {
                "id": "5567",
                "slug": "thin",
                "price": "$18.75"
            }
        },
        {
            "name": "Thin Italic",
            "description": "i1",
            "url": "http://fontdeck.com/font/fselliotwebcyrillic/thinitalic",
            "css": {
                "font-family": "FSElliotWebCyrillicThinItalic",
                "font-weight": "100",
                "font-style": "italic"
            },
            "fontdeck": {
                "id": "5568",
                "slug": "thinitalic",
                "price": "$18.75"
            }
        },
        {
            "name": "Light",
            "description": "n2",
            "url": "http://fontdeck.com/font/fselliotwebcyrillic/light",
            "css": {
                "font-family": "FS Elliot Web Cyrillic Light",
                "font-weight": "200",
                "font-style": "normal"
            },
            "fontdeck": {
                "id": "5564",
                "slug": "light",
                "price": "$18.75"
            }
        },
        {
            "name": "Light Italic",
            "description": "i2",
            "url": "http://fontdeck.com/font/fselliotwebcyrillic/lightitalic",
            "css": {
                "font-family": "FSElliotWebCyrillicLightItalic",
                "font-weight": "200",
                "font-style": "italic"
            },
            "fontdeck": {
                "id": "5565",
                "slug": "lightitalic",
                "price": "$18.75"
            }
        },
        {
            "name": "Regular",
            "description": "n4",
            "url": "http://fontdeck.com/font/fselliotwebcyrillic/regular",
            "css": {
                "font-family": "FS Elliot Web Cyrillic Regular",
                "font-weight": "400",
                "font-style": "normal"
            },
            "fontdeck": {
                "id": "5566",
                "slug": "regular",
                "price": "$18.75"
            }
        },
        {
            "name": "Regular Italic",
            "description": "i4",
            "url": "http://fontdeck.com/font/fselliotwebcyrillic/italic",
            "css": {
                "font-family": "FS Elliot Web Cyrillic Italic",
                "font-weight": "400",
                "font-style": "italic"
            },
            "fontdeck": {
                "id": "5563",
                "slug": "italic",
                "price": "$18.75"
            }
        },
        {
            "name": "Bold",
            "description": "n7",
            "url": "http://fontdeck.com/font/fselliotwebcyrillic/bold",
            "css": {
                "font-family": "FS Elliot Web Cyrillic Bold",
                "font-weight": "700",
                "font-style": "normal"
            },
            "fontdeck": {
                "id": "5559",
                "slug": "bold",
                "price": "$18.75"
            }
        },
        {
            "name": "Bold Italic",
            "description": "i7",
            "url": "http://fontdeck.com/font/fselliotwebcyrillic/bolditalic",
            "css": {
                "font-family": "FSElliotWebCyrillicBoldItalic",
                "font-weight": "700",
                "font-style": "italic"
            },
            "fontdeck": {
                "id": "5560",
                "slug": "bolditalic",
                "price": "$18.75"
            }
        },
        {
            "name": "Heavy",
            "description": "n8",
            "url": "http://fontdeck.com/font/fselliotwebcyrillic/heavy",
            "css": {
                "font-family": "FS Elliot Web Cyrillic Heavy",
                "font-weight": "800",
                "font-style": "normal"
            },
            "fontdeck": {
                "id": "5561",
                "slug": "heavy",
                "price": "$18.75"
            }
        },
        {
            "name": "Heavy Italic",
            "description": "i8",
            "url": "http://fontdeck.com/font/fselliotwebcyrillic/heavyitalic",
            "css": {
                "font-family": "FSElliotWebCyrillicHeavyItalic",
                "font-weight": "800",
                "font-style": "italic"
            },
            "fontdeck": {
                "id": "5562",
                "slug": "heavyitalic",
                "price": "$18.75"
            }
        }
    ],
    "fontdeck": {
        "id": "1294",
        "slug": "fselliotwebcyrillic"
    },
    "generatedAt": 1437610680891
}