{
    "name": "Home Text",
    "url": "http://fontdeck.com/typeface/hometext",
    "slug": "hometext",
    "use": "body",
    "classification": [
        "Serif",
        "Garalde"
    ],
    "foundry": "Playtype",
    "designer": [
        "Jonas Hecksher"
    ],
    "language": [
        "latin"
    ],
    "tags": [
        "branding",
        "readability",
        "garalde",
        "screen",
        "modern font"
    ],
    "variations": [
        {
            "name": "Regular",
            "description": "n4",
            "url": "http://fontdeck.com/font/hometext/regular",
            "css": {
                "font-family": "Home Text Regular",
                "font-weight": "400",
                "font-style": "normal"
            },
            "fontdeck": {
                "id": "5243",
                "slug": "regular",
                "price": "$45.00"
            }
        },
        {
            "name": "Regular Italic",
            "description": "i4",
            "url": "http://fontdeck.com/font/hometext/italic",
            "css": {
                "font-family": "Home Text Italic",
                "font-weight": "400",
                "font-style": "italic"
            },
            "fontdeck": {
                "id": "5240",
                "slug": "italic",
                "price": "$45.00"
            }
        },
        {
            "name": "Bold",
            "description": "n7",
            "url": "http://fontdeck.com/font/hometext/bold",
            "css": {
                "font-family": "Home Text Bold",
                "font-weight": "700",
                "font-style": "normal"
            },
            "fontdeck": {
                "id": "5242",
                "slug": "bold",
                "price": "$45.00"
            }
        },
        {
            "name": "DemiBold",
            "description": "n6",
            "url": "http://fontdeck.com/font/hometext/demibold",
            "css": {
                "font-family": "Home Text DemiBold",
                "font-weight": "600",
                "font-style": "normal"
            },
            "fontdeck": {
                "id": "5241",
                "slug": "demibold",
                "price": "$45.00"
            }
        }
    ],
    "fontdeck": {
        "id": "1209",
        "slug": "hometext"
    },
    "generatedAt": 1437610583396
}