{
    "name": "Battersea",
    "url": "http://fontdeck.com/typeface/battersea",
    "slug": "battersea",
    "superfamily": "Battersea",
    "use": "heading",
    "classification": [
        "Display",
        "Sans serif",
        "Sans Serif",
        "Grotesque"
    ],
    "foundry": "A2-TYPE",
    "designer": [
        "Henrik Kubel"
    ],
    "language": [
        "latin"
    ],
    "tags": [
        "book",
        "text",
        "legible",
        "editorial",
        "contemporary",
        "newspaper",
        "magazine",
        "superfamily"
    ],
    "variations": [
        {
            "name": "Thin",
            "description": "n1",
            "url": "http://fontdeck.com/font/battersea/thin",
            "css": {
                "font-family": "Battersea Thin",
                "font-weight": "100",
                "font-style": "normal"
            },
            "fontdeck": {
                "id": "6403",
                "slug": "thin",
                "price": "$45.00"
            }
        },
        {
            "name": "Thin Italic",
            "description": "i1",
            "url": "http://fontdeck.com/font/battersea/thinitalic",
            "css": {
                "font-family": "Battersea Thin Italic",
                "font-weight": "100",
                "font-style": "italic"
            },
            "fontdeck": {
                "id": "6404",
                "slug": "thinitalic",
                "price": "$45.00"
            }
        },
        {
            "name": "Light",
            "description": "n2",
            "url": "http://fontdeck.com/font/battersea/light",
            "css": {
                "font-family": "Battersea Light",
                "font-weight": "200",
                "font-style": "normal"
            },
            "fontdeck": {
                "id": "6397",
                "slug": "light",
                "price": "$45.00"
            }
        },
        {
            "name": "Light Italic",
            "description": "i2",
            "url": "http://fontdeck.com/font/battersea/lightitalic",
            "css": {
                "font-family": "Battersea Light Italic",
                "font-weight": "200",
                "font-style": "italic"
            },
            "fontdeck": {
                "id": "6399",
                "slug": "lightitalic",
                "price": "$45.00"
            }
        },
        {
            "name": "Regular",
            "description": "n4",
            "url": "http://fontdeck.com/font/battersea/regular",
            "css": {
                "font-family": "Battersea Regular",
                "font-weight": "400",
                "font-style": "normal"
            },
            "fontdeck": {
                "id": "6405",
                "slug": "regular",
                "price": "$45.00"
            }
        },
        {
            "name": "Regular Italic",
            "description": "i4",
            "url": "http://fontdeck.com/font/battersea/italic",
            "css": {
                "font-family": "Battersea Italic",
                "font-weight": "400",
                "font-style": "italic"
            },
            "fontdeck": {
                "id": "6396",
                "slug": "italic",
                "price": "$45.00"
            }
        },
        {
            "name": "Medium",
            "description": "n5",
            "url": "http://fontdeck.com/font/battersea/medium",
            "css": {
                "font-family": "Battersea Medium",
                "font-weight": "500",
                "font-style": "normal"
            },
            "fontdeck": {
                "id": "6398",
                "slug": "medium",
                "price": "$45.00"
            }
        },
        {
            "name": "Medium Italic",
            "description": "i5",
            "url": "http://fontdeck.com/font/battersea/mediumitalic",
            "css": {
                "font-family": "Battersea Medium Italic",
                "font-weight": "500",
                "font-style": "italic"
            },
            "fontdeck": {
                "id": "6400",
                "slug": "mediumitalic",
                "price": "$45.00"
            }
        },
        {
            "name": "Semi-bold",
            "description": "n3",
            "url": "http://fontdeck.com/font/battersea/semibold",
            "css": {
                "font-family": "Battersea SemiBold",
                "font-weight": "300",
                "font-style": "normal"
            },
            "fontdeck": {
                "id": "6401",
                "slug": "semibold",
                "price": "$45.00"
            }
        },
        {
            "name": "Semi-bold Italic",
            "description": "i3",
            "url": "http://fontdeck.com/font/battersea/semibolditalic",
            "css": {
                "font-family": "Battersea SemiBold Italic",
                "font-weight": "300",
                "font-style": "italic"
            },
            "fontdeck": {
                "id": "6402",
                "slug": "semibolditalic",
                "price": "$45.00"
            }
        },
        {
            "name": "Bold",
            "description": "n7",
            "url": "http://fontdeck.com/font/battersea/bold",
            "css": {
                "font-family": "Battersea Bold",
                "font-weight": "700",
                "font-style": "normal"
            },
            "fontdeck": {
                "id": "6392",
                "slug": "bold",
                "price": "$45.00"
            }
        },
        {
            "name": "Bold Italic",
            "description": "i7",
            "url": "http://fontdeck.com/font/battersea/bolditalic",
            "css": {
                "font-family": "Battersea Bold Italic",
                "font-weight": "700",
                "font-style": "italic"
            },
            "fontdeck": {
                "id": "6393",
                "slug": "bolditalic",
                "price": "$45.00"
            }
        },
        {
            "name": "Extra-bold",
            "description": "n8",
            "url": "http://fontdeck.com/font/battersea/extrabold",
            "css": {
                "font-family": "Battersea Extra Bold",
                "font-weight": "800",
                "font-style": "normal"
            },
            "fontdeck": {
                "id": "6394",
                "slug": "extrabold",
                "price": "$45.00"
            }
        },
        {
            "name": "Extra-bold Italic",
            "description": "i8",
            "url": "http://fontdeck.com/font/battersea/extrabolditalic",
            "css": {
                "font-family": "Battersea Extra Bold Italic",
                "font-weight": "800",
                "font-style": "italic"
            },
            "fontdeck": {
                "id": "6395",
                "slug": "extrabolditalic",
                "price": "$45.00"
            }
        }
    ],
    "fontdeck": {
        "id": "1465",
        "slug": "battersea"
    },
    "generatedAt": 1437610901665
}